paxjaxlib/__init__.py
paxjaxlib/activations.py
paxjaxlib/core.py
paxjaxlib/initializers.py
paxjaxlib/layers.py
paxjaxlib/losses.py
paxjaxlib/metrics.py
paxjaxlib/models.py
paxjaxlib/regularizers.py
paxjaxlib/schedules.py
paxjaxlib/training.py
paxjaxlib-0.1.2.dist-info/licenses/LICENSE
paxjaxlib-0.1.2.dist-info/METADATA
paxjaxlib-0.1.2.dist-info/WHEEL
paxjaxlib-0.1.2.dist-info/top_level.txt
paxjaxlib-0.1.2.dist-info/RECORD
