Metadata-Version: 2.4
Name: paxjaxlib
Version: 0.1.2
Summary: A simple neural network implementation using JAX, made for educational purposes
Author-email: Igor Beketov <paxamans@gmail.com>
License: MIT
Project-URL: Homepage, https://github.com/paxamans/paxjaxlib
Keywords: neural network,deep learning,jax
Classifier: Programming Language :: Python :: 3
Classifier: Operating System :: OS Independent
Requires-Python: >=3.13
License-File: LICENSE
Requires-Dist: jax
Requires-Dist: jaxlib
Requires-Dist: numpy
Requires-Dist: optax
Provides-Extra: dev
Requires-Dist: pytest; extra == "dev"
Requires-Dist: ruff; extra == "dev"
Requires-Dist: mypy; extra == "dev"
Requires-Dist: pre-commit; extra == "dev"
Dynamic: license-file
